cryptlab/__init__.py
cryptlab/client/__init__.py
cryptlab/client/common.py
cryptlab/client/local.py
cryptlab/client/orchestrated.py
cryptlab/client/pki.py
cryptlab/client/util.py
cryptlab/common/__init__.py
cryptlab/common/broadcaster.py
cryptlab/common/cfg.py
cryptlab/common/exceptions.py
cryptlab/common/messages.py
cryptlab/common/utils/__init__.py
cryptlab/common/utils/namegen.py
cryptlab/entrypoint.py
cryptlab/orchestrator/__init__.py
cryptlab/orchestrator/clients/__init__.py
cryptlab/orchestrator/clients/validator.py
cryptlab/orchestrator/clients/wslistener.py
cryptlab/orchestrator/dependencies.py
cryptlab/orchestrator/logger.py
cryptlab/orchestrator/main.py
cryptlab/orchestrator/pages/challenge.html
cryptlab/orchestrator/routers/__init__.py
cryptlab/orchestrator/routers/challenge.py
cryptlab/orchestrator/routers/healthcheck.py
cryptlab/orchestrator/routers/root.py
cryptlab/orchestrator/routers/websocket.py
cryptlab/orchestrator/serverscripts/bridge.py
cryptlab/orchestrator/serverscripts/tcphandler.py
cryptlab/serverscript/__init__.py
cryptlab/serverscript/baseserver.py
cryptlab-0.1.1.dist-info/METADATA
cryptlab-0.1.1.dist-info/WHEEL
cryptlab-0.1.1.dist-info/entry_points.txt
cryptlab-0.1.1.dist-info/RECORD
