Metadata-Version: 2.1
Name: cryptlab
Version: 0.1.1
Summary: A framework for CTF challenges in a malicious-server setting
License: GPL-3.0-or-later
Author: Kien Tuong Truong
Author-email: info@ktruong.dev
Requires-Python: >=3.11,<4.0
Classifier: License :: OSI Approved :: GNU General Public License v3 or later (GPLv3+)
Classifier: Programming Language :: Python :: 3
Classifier: Programming Language :: Python :: 3.11
Classifier: Programming Language :: Python :: 3.12
Requires-Dist: fastapi (>=0.111.0,<0.112.0)
Requires-Dist: loguru (>=0.7.2,<0.8.0)
Requires-Dist: pycryptodome (>=3.20.0,<4.0.0)
Requires-Dist: python-decouple (>=3.8,<4.0)
Requires-Dist: requests (>=2.32.2,<3.0.0)
Requires-Dist: uvicorn (>=0.29.0,<0.30.0)
